openhexa/toolbox/dhis2/__init__.py
openhexa/toolbox/dhis2/api.py
openhexa/toolbox/dhis2/dataframe.py
openhexa/toolbox/dhis2/dhis2.py
openhexa/toolbox/dhis2/periods.py
openhexa/toolbox/era5/__init__.py
openhexa/toolbox/era5/cache.py
openhexa/toolbox/era5/dhis2weeks.py
openhexa/toolbox/era5/extract.py
openhexa/toolbox/era5/models.py
openhexa/toolbox/era5/transform.py
openhexa/toolbox/era5/utils.py
openhexa/toolbox/era5/data/variables.toml
openhexa/toolbox/hexa/__init__.py
openhexa/toolbox/hexa/api.py
openhexa/toolbox/hexa/hexa.py
openhexa/toolbox/iaso/__init__.py
openhexa/toolbox/iaso/api_client.py
openhexa/toolbox/iaso/dataframe.py
openhexa/toolbox/iaso/iaso.py
openhexa/toolbox/kobo/__init__.py
openhexa/toolbox/kobo/api.py
openhexa/toolbox/kobo/parse.py
openhexa/toolbox/kobo/utils.py
openhexa/toolbox/lineage/__init__.py
openhexa/toolbox/lineage/client.py
openhexa_toolbox-2.10.0.dist-info/licenses/LICENSE
openhexa_toolbox-2.10.0.dist-info/METADATA
openhexa_toolbox-2.10.0.dist-info/WHEEL
openhexa_toolbox-2.10.0.dist-info/top_level.txt
openhexa_toolbox-2.10.0.dist-info/RECORD
