Metadata-Version: 2.4
Name: openhexa.toolbox
Version: 2.10.0
Summary: A set of tools to acquire & process data from various sources
Author-email: Bluesquare <dev@bluesquarehub.com>
Maintainer-email: Bluesquare <dev@bluesquarehub.com>
License: MIT License
Project-URL: Homepage, https://github.com/blsq/openhexa-toolbox
Project-URL: Bug Tracker, https://github.com/blsq/openhexa-toolbox/issues
Classifier: Programming Language :: Python :: 3
Classifier: License :: OSI Approved :: MIT License
Classifier: Operating System :: OS Independent
Requires-Python: >=3.12
License-File: LICENSE
Requires-Dist: requests
Requires-Dist: python-dateutil
Requires-Dist: pandas
Requires-Dist: shapely
Requires-Dist: geopandas
Requires-Dist: fiona
Requires-Dist: polars>=1.0
Requires-Dist: diskcache
Requires-Dist: pyjwt
Requires-Dist: rasterio
Requires-Dist: epiweeks
Requires-Dist: openhexa.sdk
Requires-Dist: humanize
Requires-Dist: rich
Requires-Dist: psycopg>=3.2.11
Requires-Dist: regex
Provides-Extra: dev
Requires-Dist: ruff~=0.12.12; extra == "dev"
Requires-Dist: pytest~=8.4.0; extra == "dev"
Requires-Dist: pytest-cov~=7.0.0; extra == "dev"
Requires-Dist: build~=1.3.0; extra == "dev"
Requires-Dist: black~=25.1.0; extra == "dev"
Requires-Dist: pre-commit; extra == "dev"
Requires-Dist: responses; extra == "dev"
Provides-Extra: test
Requires-Dist: ruff~=0.12.12; extra == "test"
Requires-Dist: pytest~=8.4.0; extra == "test"
Requires-Dist: pytest-cov~=7.0.0; extra == "test"
Requires-Dist: responses; extra == "test"
Requires-Dist: xarray; extra == "test"
Requires-Dist: rasterio; extra == "test"
Requires-Dist: epiweeks; extra == "test"
Requires-Dist: openlineage-python>=1.33.0; extra == "test"
Requires-Dist: ecmwf-datastores-client>=0.4.0; extra == "test"
Requires-Dist: pyarrow>=18.1.0; extra == "test"
Requires-Dist: xarray>=2025.9.1; extra == "test"
Requires-Dist: zarr>=3.1.3; extra == "test"
Provides-Extra: era5
Requires-Dist: cfgrib>=0.9.15.1; extra == "era5"
Requires-Dist: ecmwf-datastores-client>=0.4.0; extra == "era5"
Requires-Dist: pyarrow>=21.0.0; extra == "era5"
Requires-Dist: xarray>=2025.9.1; extra == "era5"
Requires-Dist: zarr>=3.1.3; extra == "era5"
Requires-Dist: dask; extra == "era5"
Provides-Extra: lineage
Requires-Dist: openlineage-python>=1.33.0; extra == "lineage"
Provides-Extra: all
Dynamic: license-file
